topsis_disha_102303141/__init__.py
topsis_disha_102303141/topsis.py
topsis_disha_102303141-0.0.1.dist-info/METADATA
topsis_disha_102303141-0.0.1.dist-info/WHEEL
topsis_disha_102303141-0.0.1.dist-info/entry_points.txt
topsis_disha_102303141-0.0.1.dist-info/top_level.txt
topsis_disha_102303141-0.0.1.dist-info/RECORD
