Metadata-Version: 2.4
Name: Topsis-Disha-102303141
Version: 0.0.1
Summary: TOPSIS package for MCDM problems
Author: Disha Malik
Author-email: dmalik_be23@thapar.edu
License: MIT
Requires-Python: >=3.6
Requires-Dist: numpy
Requires-Dist: pandas
Dynamic: author
Dynamic: author-email
Dynamic: description
Dynamic: description-content-type
Dynamic: license
Dynamic: requires-dist
Dynamic: requires-python
Dynamic: summary
